{
  "index": "35",
  "name": "Shrine of Thelija",
  "edition": "fc",
  "parent": "106",
  "marker": "2",
  "monsters": [
    "ancient-artillery",
    "frost-demon",
    "savvas-icestorm",
    "wind-demon"
  ],
  "rules": [
    {
      "round": "true",
      "always": true,
      "alwaysApply": true,
      "statEffects": [
        {
          "identifier": {
            "type": "monster",
            "edition": "gh",
            "name": "savvas-icestorm"
          },
          "statEffect": {
            "name": "avatar-of-thelija",
            "count": 1
          },
          "note": "%data.section.rules.fc.35%"
        }
      ]
    }
  ],
  "rooms": [
    {
      "roomNumber": 3,
      "ref": "D2a",
      "initial": true,
      "monster": [
        {
          "name": "ancient-artillery",
          "player2": "normal",
          "player3": "elite",
          "player4": "normal"
        },
        {
          "name": "ancient-artillery",
          "player2": "elite",
          "player3": "normal",
          "player4": "normal"
        },
        {
          "name": "frost-demon",
          "player3": "normal",
          "player4": "elite"
        },
        {
          "name": "savvas-icestorm",
          "player2": "normal",
          "player3": "normal",
          "player4": "elite"
        },
        {
          "name": "wind-demon",
          "player3": "normal",
          "player4": "elite"
        }
      ]
    }
  ]
}