{
  "index": "100",
  "name": "Shifting Gears",
  "flowChartGroup": "the-rift",
  "coordinates": {
    "x": 1318.25,
    "y": 651.75,
    "width": 181,
    "height": 119,
    "gridLocation": "E-9"
  },
  "edition": "fc",
  "eventType": "rift",
  "monsters": [
    "stone-golem"
  ],
  "rooms": [
    {
      "roomNumber": 1,
      "ref": "F1a",
      "initial": true,
      "monster": [
        {
          "name": "stone-golem",
          "player2": "normal",
          "player3": "normal",
          "player4": "elite"
        },
        {
          "name": "stone-golem",
          "player3": "normal",
          "player4": "normal"
        }
      ]
    }
  ]
}