{
  "index": "59",
  "name": "Forest Invaders",
  "edition": "cs",
  "rewards": {
    "items": [
      "47"
    ]
  },
  "monsters": [
    "giant-viper",
    "vermling-scout"
  ],
  "rules": [
    {
      "round": "R == 2",
      "spawns": [
        {
          "monster": {
            "name": "vermling-scout",
            "type": "normal"
          },
          "marker": "a"
        },
        {
          "monster": {
            "name": "giant-viper",
            "type": "elite"
          },
          "marker": "a"
        }
      ]
    }
  ],
  "rooms": [
    {
      "roomNumber": 1,
      "ref": "b1",
      "initial": true,
      "monster": [
        {
          "name": "giant-viper",
          "type": "elite"
        },
        {
          "name": "vermling-scout",
          "type": "normal"
        }
      ]
    }
  ]
}