{
  "index": "15",
  "name": "Shrine of Strength",
  "edition": "gh",
  "monsters": [
    "frost-demon",
    "harrower-infester",
    "savvas-icestorm",
    "stone-golem",
    "wind-demon"
  ],
  "rooms": [
    {
      "roomNumber": 1,
      "ref": "l1a",
      "initial": true,
      "doors": [
        2
      ],
      "monster": [
        {
          "name": "stone-golem",
          "player4": "normal"
        },
        {
          "name": "stone-golem",
          "player3": "normal",
          "player4": "normal"
        },
        {
          "name": "savvas-icestorm",
          "type": "elite"
        }
      ]
    },
    {
      "roomNumber": 2,
      "ref": "d1a",
      "doors": [
        3,
        4,
        5
      ],
      "monster": [
        {
          "name": "frost-demon",
          "type": "normal"
        },
        {
          "name": "frost-demon",
          "type": "normal"
        },
        {
          "name": "wind-demon",
          "player3": "normal",
          "player4": "elite"
        },
        {
          "name": "wind-demon",
          "player3": "normal",
          "player4": "elite"
        },
        {
          "name": "savvas-icestorm",
          "type": "normal"
        }
      ]
    },
    {
      "roomNumber": 3,
      "marker": "a",
      "ref": "h3b",
      "monster": [
        {
          "name": "stone-golem",
          "player3": "normal",
          "player4": "normal"
        },
        {
          "name": "harrower-infester",
          "player3": "normal",
          "player4": "normal"
        },
        {
          "name": "harrower-infester",
          "type": "elite"
        }
      ]
    },
    {
      "roomNumber": 4,
      "marker": "a",
      "ref": "h1b",
      "monster": [
        {
          "name": "stone-golem",
          "player4": "normal"
        },
        {
          "name": "harrower-infester",
          "player4": "normal"
        },
        {
          "name": "harrower-infester",
          "type": "elite"
        }
      ]
    },
    {
      "roomNumber": 5,
      "marker": "b",
      "ref": "c1a",
      "treasures": [
        -1
      ],
      "monster": [
        {
          "name": "stone-golem",
          "type": "elite"
        },
        {
          "name": "stone-golem",
          "type": "elite"
        }
      ]
    }
  ]
}